grater_jax/__init__.py
grater_jax/disk_model/SLD_ojax.py
grater_jax/disk_model/SLD_utils.py
grater_jax/disk_model/__init__.py
grater_jax/disk_model/interpolated_univariate_spline.py
grater_jax/disk_model/jax_gradient_wrappers.py
grater_jax/disk_model/jax_model_wrappers.py
grater_jax/disk_model/objective_functions.py
grater_jax/disk_model/winnie_class.py
grater_jax/disk_model/winnie_jwst_fm.py
grater_jax/optimization/__init__.py
grater_jax/optimization/mcmc_model.py
grater_jax/optimization/optimize_framework.py
grater_jax-0.2.3.dist-info/licenses/LICENSE
grater_jax-0.2.3.dist-info/METADATA
grater_jax-0.2.3.dist-info/WHEEL
grater_jax-0.2.3.dist-info/top_level.txt
grater_jax-0.2.3.dist-info/RECORD
