Metadata-Version: 2.4
Name: grater-jax
Version: 0.2.3
Summary: JAX-powered machine learning and modeling framework for GRaTeR disks.
Author-email: Mihir Kondapalli <mihir.kondapalli@gmail.com>, Briley Lewis <brileylewis@g.ucla.edu>
License: MIT
Requires-Python: <3.13,>=3.9
License-File: LICENSE
Requires-Dist: numpy<2.0,>=1.23
Requires-Dist: scipy<=1.14,>=1.10
Requires-Dist: matplotlib<3.9,>=3.7
Requires-Dist: pandas<2.3,>=1.5
Requires-Dist: astropy<7.0,>=5.3
Requires-Dist: astroquery<0.5,>=0.4
Requires-Dist: poppy<1.2,>=1.0
Requires-Dist: stsynphot<1.5,>=1.3
Requires-Dist: synphot<1.5,>=1.3
Requires-Dist: pysiaf<0.24,>=0.21
Requires-Dist: emcee<3.2,>=3.1
Requires-Dist: arviz<0.18,>=0.15
Requires-Dist: corner<2.3,>=2.2
Requires-Dist: xarray<2024.10,>=2023.1
Requires-Dist: jax<=0.4.34,>=0.4.20
Requires-Dist: jaxlib<=0.4.34,>=0.4.20
Requires-Dist: jaxopt<0.9,>=0.8
Requires-Dist: tqdm<5.0,>=4.65
Provides-Extra: dev
Requires-Dist: pytest<9.0,>=7.0; extra == "dev"
Requires-Dist: vip_hci>=1.3; extra == "dev"
Provides-Extra: docs
Requires-Dist: sphinx<8.0,>=7.2; extra == "docs"
Requires-Dist: sphinx-rtd-theme<2.1,>=1.3; extra == "docs"
Requires-Dist: myst-parser<3.1,>=2.0; extra == "docs"
Requires-Dist: nbsphinx<0.10,>=0.9; extra == "docs"
Requires-Dist: photutils<1.14,>=1.8; extra == "docs"
Provides-Extra: webbpsf
Requires-Dist: webbpsf<1.4,>=1.0; extra == "webbpsf"
Requires-Dist: webbpsf_ext<1.4,>=1.0; extra == "webbpsf"
Requires-Dist: poppy<1.2,>=1.0; extra == "webbpsf"
Dynamic: license-file
